tableauserverconnection/tableauserverconnection.py
tableauserverconnection-0.0.4.dist-info/METADATA
tableauserverconnection-0.0.4.dist-info/WHEEL
tableauserverconnection-0.0.4.dist-info/top_level.txt
tableauserverconnection-0.0.4.dist-info/RECORD
