Metadata-Version: 2.1
Name: tableauserverconnection
Version: 0.0.4
Summary: Package to extend tableauserverclient with further functions
Home-page: UNKNOWN
Author: Edward Oldham
Author-email: <edward.oldham@me.com>
License: UNKNOWN
Keywords: tableau,refresh data source,refresh workbook
Platform: UNKNOWN
Classifier: Development Status :: 3 - Alpha
Classifier: Intended Audience :: Education
Classifier: Programming Language :: Python :: 2
Classifier: Programming Language :: Python :: 3
Classifier: Operating System :: MacOS :: MacOS X
Classifier: Operating System :: Microsoft :: Windows
Requires-Dist: tableauserverclient
